asdk_plugin_platform/__init__.py
asdk_plugin_platform/api_registry.py
asdk_plugin_platform/domain_apis_list.json
asdk_plugin_platform/agraph/__init__.py
asdk_plugin_platform/agraph/platform/__init__.py
asdk_plugin_platform/agraph/platform/access/__init__.py
asdk_plugin_platform/agraph/platform/access/permission/__init__.py
asdk_plugin_platform/agraph/platform/access/permission/v1/__init__.py
asdk_plugin_platform/agraph/platform/access/permission/v1/PermissionAPI/__init__.py
asdk_plugin_platform/agraph/platform/access/permission/v1/PermissionAPI/api_client.py
asdk_plugin_platform/agraph/platform/access/permission/v1/PermissionAPI/api_response.py
asdk_plugin_platform/agraph/platform/access/permission/v1/PermissionAPI/configuration.py
asdk_plugin_platform/agraph/platform/access/permission/v1/PermissionAPI/exceptions.py
asdk_plugin_platform/agraph/platform/access/permission/v1/PermissionAPI/rest.py
asdk_plugin_platform/agraph/platform/access/permission/v1/PermissionAPI/swagger.json
asdk_plugin_platform/agraph/platform/access/permission/v1/PermissionAPI/api/__init__.py
asdk_plugin_platform/agraph/platform/access/permission/v1/PermissionAPI/api/default_permission_api.py
asdk_plugin_platform/agraph/platform/access/permission/v1/PermissionAPI/models/__init__.py
asdk_plugin_platform/agraph/platform/access/permission/v1/PermissionAPI/models/any.py
asdk_plugin_platform/agraph/platform/access/permission/v1/PermissionAPI/models/permission_api_get_permission400_response.py
asdk_plugin_platform/agraph/platform/access/permission/v1/PermissionAPI/models/rpc_status.py
asdk_plugin_platform/agraph/platform/access/permission/v1/PermissionAPI/models/v1_filter_permissions_request.py
asdk_plugin_platform/agraph/platform/access/permission/v1/PermissionAPI/models/v1_filter_permissions_response.py
asdk_plugin_platform/agraph/platform/access/permission/v1/PermissionAPI/models/v1_permission.py
asdk_plugin_platform/agraph/platform/access/permission/v1/PermissionAPI/models/v1_permission_query.py
asdk_plugin_platform-2.0.0b2.dist-info/METADATA
asdk_plugin_platform-2.0.0b2.dist-info/WHEEL
asdk_plugin_platform-2.0.0b2.dist-info/top_level.txt
asdk_plugin_platform-2.0.0b2.dist-info/RECORD
